main.py
choose_mcp_server-0.1.10.dist-info/METADATA
choose_mcp_server-0.1.10.dist-info/WHEEL
choose_mcp_server-0.1.10.dist-info/entry_points.txt
choose_mcp_server-0.1.10.dist-info/top_level.txt
choose_mcp_server-0.1.10.dist-info/RECORD
