Metadata-Version: 2.2
Name: choose-mcp-server
Version: 0.1.10
Summary: Add your description here
Requires-Python: >=3.10.6
Requires-Dist: google-cloud-bigquery>=3.29.0
Requires-Dist: mcp[cli]>=1.3.0
